mkdocs_material_ekgf/__init__.py
mkdocs_material_ekgf/config.py
mkdocs_material_ekgf/main.html
mkdocs_material_ekgf/mkdocs_theme.yml
mkdocs_material_ekgf/social.py
mkdocs_material_ekgf/assets/javascripts/images_dark.js
mkdocs_material_ekgf/assets/javascripts/nav-section-links.js
mkdocs_material_ekgf/assets/javascripts/refresh_on_toggle_dark_light.js
mkdocs_material_ekgf/assets/javascripts/tabbed-url-sync.js
mkdocs_material_ekgf/assets/stylesheets/ekgf-theme.css
mkdocs_material_ekgf/partials/content.html
mkdocs_material_ekgf/partials/ekgf-logo.html
mkdocs_material_ekgf/partials/footer.html
mkdocs_material_ekgf/partials/header.html
mkdocs_material_ekgf/partials/omg-logo.html
mkdocs_material_ekgf/partials/palette.html
mkdocs_material_ekgf/partials/search-box.html
mkdocs_material_ekgf/partials/seo.html
mkdocs_material_ekgf/partials/social-card.html
mkdocs_material_ekgf/partials/tabs.html
mkdocs_material_ekgf-0.0.23.dist-info/METADATA
mkdocs_material_ekgf-0.0.23.dist-info/WHEEL
mkdocs_material_ekgf-0.0.23.dist-info/entry_points.txt
mkdocs_material_ekgf-0.0.23.dist-info/licenses/LICENSE
mkdocs_material_ekgf-0.0.23.dist-info/RECORD
