Metadata-Version: 2.4
Name: mkdocs-material-ekgf
Version: 0.0.23
Summary: A custom Material for MkDocs theme for EKGF documentation websites
Project-URL: Homepage, https://ekgf.org
Project-URL: Documentation, https://github.com/EKGF/mkdocs-material-ekgf
Project-URL: Repository, https://github.com/EKGF/mkdocs-material-ekgf
Project-URL: Issues, https://github.com/EKGF/mkdocs-material-ekgf/issues
Author-email: Jacobus Geluk <jacobus.geluk@ekgf.org>
License: Copyright (c) 2026 EDMCouncil Inc., d/b/a Enterprise Data Management Association ("EDMA")
License-File: LICENSE
Classifier: Development Status :: 4 - Beta
Classifier: Intended Audience :: Developers
Classifier: Programming Language :: Python :: 3
Classifier: Programming Language :: Python :: 3.14
Classifier: Topic :: Documentation
Classifier: Topic :: Software Development :: Documentation
Requires-Python: >=3.14.2
Requires-Dist: mkdocs-material>=9.0.0
Requires-Dist: mkdocs>=1.5.0
Provides-Extra: dev
Requires-Dist: mypy>=1.11.0; extra == 'dev'
Requires-Dist: pytest>=8.3.0; extra == 'dev'
Requires-Dist: ruff>=0.8.0; extra == 'dev'
Requires-Dist: twine>=5.0.0; extra == 'dev'
Provides-Extra: social
Requires-Dist: playwright>=1.40.0; extra == 'social'
